stix/__init__.py
stix/base.py
stix/data_marking.py
stix/version.py
stix/xmlconst.py
stix/bindings/__init__.py
stix/bindings/campaign.py
stix/bindings/course_of_action.py
stix/bindings/data_marking.py
stix/bindings/exploit_target.py
stix/bindings/incident.py
stix/bindings/indicator.py
stix/bindings/report.py
stix/bindings/stix_common.py
stix/bindings/stix_core.py
stix/bindings/threat_actor.py
stix/bindings/ttp.py
stix/bindings/extensions/__init__.py
stix/bindings/extensions/address/__init__.py
stix/bindings/extensions/address/ciq_address_3_0.py
stix/bindings/extensions/attack_pattern/__init__.py
stix/bindings/extensions/attack_pattern/capec_2_7.py
stix/bindings/extensions/identity/__init__.py
stix/bindings/extensions/identity/ciq_identity_3_0.py
stix/bindings/extensions/malware/__init__.py
stix/bindings/extensions/malware/maec_4_1.py
stix/bindings/extensions/marking/__init__.py
stix/bindings/extensions/marking/simple_marking.py
stix/bindings/extensions/marking/terms_of_use_marking.py
stix/bindings/extensions/marking/tlp.py
stix/bindings/extensions/structured_coa/__init__.py
stix/bindings/extensions/structured_coa/generic.py
stix/bindings/extensions/test_mechanism/__init__.py
stix/bindings/extensions/test_mechanism/generic.py
stix/bindings/extensions/test_mechanism/open_ioc_2010.py
stix/bindings/extensions/test_mechanism/oval_5_10.py
stix/bindings/extensions/test_mechanism/snort.py
stix/bindings/extensions/test_mechanism/yara.py
stix/bindings/extensions/vulnerability/__init__.py
stix/bindings/extensions/vulnerability/cvrf_1_1.py
stix/campaign/__init__.py
stix/coa/__init__.py
stix/coa/objective.py
stix/coa/structured_coa.py
stix/common/__init__.py
stix/common/activity.py
stix/common/campaign_reference.py
stix/common/confidence.py
stix/common/datetimewithprecision.py
stix/common/identity.py
stix/common/information_source.py
stix/common/names.py
stix/common/profiles.py
stix/common/references.py
stix121-1.0.0a1.dist-info/DESCRIPTION.rst
stix121-1.0.0a1.dist-info/METADATA
stix121-1.0.0a1.dist-info/RECORD
stix121-1.0.0a1.dist-info/WHEEL
stix121-1.0.0a1.dist-info/metadata.json
stix121-1.0.0a1.dist-info/top_level.txt
