Metadata-Version: 2.0
Name: stix121
Version: 1.0.0a1
Summary: An API for parsing and generating STIX content.
Home-page: http://stix.mitre.org
Author: STIX Project, MITRE Corporation
Author-email: stix@mitre.org
License: UNKNOWN
Platform: UNKNOWN
Classifier: Programming Language :: Python
Classifier: Development Status :: 4 - Beta
Classifier: Intended Audience :: Developers
Classifier: License :: OSI Approved :: BSD License
Classifier: Operating System :: OS Independent
Requires-Dist: cybox211
Requires-Dist: lxml (>=2.3)
Requires-Dist: mixbox (>=1.0.1)
Requires-Dist: python-dateutil
Provides-Extra: docs
Requires-Dist: Sphinx (==1.3.1); extra == 'docs'
Requires-Dist: sphinx-rtd-theme (==0.1.8); extra == 'docs'
Provides-Extra: test
Requires-Dist: maec411; extra == 'test'
Requires-Dist: nose (==1.3.0); extra == 'test'
Requires-Dist: tox (==1.6.1); extra == 'test'
